aimsprop/__init__.py
aimsprop/atom_data.py
aimsprop/blur.py
aimsprop/bootstrap.py
aimsprop/bundle.py
aimsprop/fms90.py
aimsprop/geom.py
aimsprop/pes.py
aimsprop/plot.py
aimsprop/pop.py
aimsprop/rotate.py
aimsprop/sine.py
aimsprop/ued.py
aimsprop/units.py
aimsprop/wrap.py
aimsprop/xyz.py
aimsprop/iam/README
aimsprop/iam/__init__.py
aimsprop/iam/diffraction.py
aimsprop/iam/formfactor.py
aimsprop/iam/lebedev.py
aimsprop/iam/legendre.py
aimsprop/iam/rotation.py
aimsprop/iam/ext/Makefile
aimsprop/iam/ext/__init__.py
aimsprop/iam/ext/test.cpp
aimsprop/vis_aims/__init__.py
aimsprop/vis_aims/render.py
aimsprop/vis_aims/run.py
aimsprop/vis_aims/ref/footer.vmd
aimsprop/vis_aims/ref/header.vmd
aimsprop/vis_aims/ref/molecule.vmd
aimsprop-0.2.2.dist-info/LICENSE
aimsprop-0.2.2.dist-info/WHEEL
aimsprop-0.2.2.dist-info/METADATA
aimsprop-0.2.2.dist-info/RECORD
