Metadata-Version: 2.1
Name: aimsprop
Version: 0.2.2
Summary: A repository for the representation and manipulation of AIMS-type trajectories.
Home-page: https://mtzgroup.github.io/aimsprop/
Author: Rob Parrish
Author-email: mtzgroupadmin@gmail.com
Requires-Python: >=3.6
Classifier: Intended Audience :: Science/Research
Classifier: Operating System :: OS Independent
Classifier: Programming Language :: Python :: 3
Classifier: Programming Language :: Python
Classifier: Programming Language :: Python :: 3 :: Only
Classifier: Programming Language :: Python :: 3.6
Classifier: Programming Language :: Python :: 3.7
Classifier: Programming Language :: Python :: 3.8
Classifier: Programming Language :: Python :: 3.9
Classifier: Topic :: Software Development :: Libraries :: Python Modules
Classifier: Topic :: Software Development :: Libraries
Classifier: Topic :: Software Development
Classifier: Typing :: Typed
Classifier: License :: OSI Approved :: MIT License
Requires-Dist: numpy
Requires-Dist: matplotlib
Requires-Dist: black>=20.8b1 ; extra == "dev"
Requires-Dist: flake8 >=3.8.4 ; extra == "dev"
Requires-Dist: isort >= 5.7.0 ; extra == "dev"
Requires-Dist: pre-commit >= 2.11.1 ; extra == "dev"
Requires-Dist: autoflake >= 1.4 ; extra == "dev"
Requires-Dist: mkdocs == 1.1.2 ; extra == "doc"
Requires-Dist: mkdocs-material == 7.0.3 ; extra == "doc"
Requires-Dist: mkdocstrings == 0.15.0 ; extra == "doc"
Requires-Dist: pytest >=6.2.2 ; extra == "test"
Requires-Dist: pytest-cov >=2.10.1,<3.0.0 ; extra == "test"
Requires-Dist: coverage >=5.3.1,<6.0 ; extra == "test"
Project-URL: Documentation, https://mtzgroup.github.io/aimsprop/
Provides-Extra: dev
Provides-Extra: doc
Provides-Extra: test
